<?xml version="1.0" encoding="utf-8"?>
<!DOCTYPE fda-regional:fda-regional SYSTEM "http://www.accessdata.fda.gov/static/eCTD/us-regional-v3-3.dtd">
<?xml-stylesheet href="http://www.accessdata.fda.gov/static/eCTD/us-regional.xsl" type="text/xsl"?>
<fda-regional:fda-regional dtd-version="3.3" xmlns:fda-regional="http://www.ich.org/fda" xmlns:xlink="http://www.w3c.org/1999/xlink">
  <admin>
    <applicant-info>
<id></id>
<company-name></company-name>
<submission-description></submission-description><applicant-contacts><applicant-contact>
<applicant-contact-name applicant-contact-type="fdaact3"></applicant-contact-name>
<telephones><telephone telephone-number-type="fdatnt1">3016777737</telephone></telephones>
<emails><email>admin@humphriespcc.com</email></emails> </applicant-contact></applicant-contacts>
 </applicant-info></admin>
</fda-regional:fda-regional>